Workbook

Sheet PAINEL
A1: Trust Excel · Painel Financeiro
A2: Totais automáticos do mês atual + gastos por categoria
A4: Mês de referência | B4: 46204
A6: Total Entradas | B6: =SUMIFS(LANCAMENTOS!E:E,LANCAMENTOS!D:D,"Entrada",LANCAMENTOS!A:A,">="&$B$4,LANCAMENTOS!A:A,"<="&EOMONTH($B$4,0))
A7: Total Saídas | B7: =SUMIFS(LANCAMENTOS!E:E,LANCAMENTOS!D:D,"Saída",LANCAMENTOS!A:A,">="&$B$4,LANCAMENTOS!A:A,"<="&EOMONTH($B$4,0))
A8: Saldo do mês | B8: =B6-B7
A10: Gastos por categoria
A11: Categoria | B11: Total Saídas
A12: =IF(CATEGORIAS!A5="","",CATEGORIAS!A5) | B12: =IF(A12="","",SUMIFS(LANCAMENTOS!E:E,LANCAMENTOS!B:B,A12,LANCAMENTOS!D:D,"Saída",LANCAMENTOS!A:A,">="&$B$4,LANCAMENTOS!A:A,"<="&EOMONTH($B$4,0)))
A13: =IF(CATEGORIAS!A6="","",CATEGORIAS!A6) | B13: =IF(A13="","",SUMIFS(LANCAMENTOS!E:E,LANCAMENTOS!B:B,A13,LANCAMENTOS!D:D,"Saída",LANCAMENTOS!A:A,">="&$B$4,LANCAMENTOS!A:A,"<="&EOMONTH($B$4,0)))
A14: =IF(CATEGORIAS!A7="","",CATEGORIAS!A7) | B14: =IF(A14="","",SUMIFS(LANCAMENTOS!E:E,LANCAMENTOS!B:B,A14,LANCAMENTOS!D:D,"Saída",LANCAMENTOS!A:A,">="&$B$4,LANCAMENTOS!A:A,"<="&EOMONTH($B$4,0)))
A15: =IF(CATEGORIAS!A8="","",CATEGORIAS!A8) | B15: =IF(A15="","",SUMIFS(LANCAMENTOS!E:E,LANCAMENTOS!B:B,A15,LANCAMENTOS!D:D,"Saída",LANCAMENTOS!A:A,">="&$B$4,LANCAMENTOS!A:A,"<="&EOMONTH($B$4,0)))
A16: =IF(CATEGORIAS!A9="","",CATEGORIAS!A9) | B16: =IF(A16="","",SUMIFS(LANCAMENTOS!E:E,LANCAMENTOS!B:B,A16,LANCAMENTOS!D:D,"Saída",LANCAMENTOS!A:A,">="&$B$4,LANCAMENTOS!A:A,"<="&EOMONTH($B$4,0)))
A17: =IF(CATEGORIAS!A10="","",CATEGORIAS!A10) | B17: =IF(A17="","",SUMIFS(LANCAMENTOS!E:E,LANCAMENTOS!B:B,A17,LANCAMENTOS!D:D,"Saída",LANCAMENTOS!A:A,">="&$B$4,LANCAMENTOS!A:A,"<="&EOMONTH($B$4,0)))
A18: =IF(CATEGORIAS!A11="","",CATEGORIAS!A11) | B18: =IF(A18="","",SUMIFS(LANCAMENTOS!E:E,LANCAMENTOS!B:B,A18,LANCAMENTOS!D:D,"Saída",LANCAMENTOS!A:A,">="&$B$4,LANCAMENTOS!A:A,"<="&EOMONTH($B$4,0)))
A19: =IF(CATEGORIAS!A12="","",CATEGORIAS!A12) | B19: =IF(A19="","",SUMIFS(LANCAMENTOS!E:E,LANCAMENTOS!B:B,A19,LANCAMENTOS!D:D,"Saída",LANCAMENTOS!A:A,">="&$B$4,LANCAMENTOS!A:A,"<="&EOMONTH($B$4,0)))
A20: =IF(CATEGORIAS!A13="","",CATEGORIAS!A13) | B20: =IF(A20="","",SUMIFS(LANCAMENTOS!E:E,LANCAMENTOS!B:B,A20,LANCAMENTOS!D:D,"Saída",LANCAMENTOS!A:A,">="&$B$4,LANCAMENTOS!A:A,"<="&EOMONTH($B$4,0)))
A21: =IF(CATEGORIAS!A14="","",CATEGORIAS!A14) | B21: =IF(A21="","",SUMIFS(LANCAMENTOS!E:E,LANCAMENTOS!B:B,A21,LANCAMENTOS!D:D,"Saída",LANCAMENTOS!A:A,">="&$B$4,LANCAMENTOS!A:A,"<="&EOMONTH($B$4,0)))
A22: =IF(CATEGORIAS!A15="","",CATEGORIAS!A15) | B22: =IF(A22="","",SUMIFS(LANCAMENTOS!E:E,LANCAMENTOS!B:B,A22,LANCAMENTOS!D:D,"Saída",LANCAMENTOS!A:A,">="&$B$4,LANCAMENTOS!A:A,"<="&EOMONTH($B$4,0)))
A25: Automação TrustCorp: preencha LANCAMENTOS; o PAINEL recalcula sozinho. Use lista suspensa em Categoria e Tipo.

Sheet CATEGORIAS
A1: Trust Excel · Categorias
A2: Lista-mestre para validação de lançamentos
A4: Categoria
A5: Moradia
A6: Alimentação
A7: Transporte
A8: Lazer
A9: Assinaturas
A10: Saúde
A11: Educação
A12: Salário
A13: Freelance
... A15: Outros

Sheet LANCAMENTOS
A1: Trust Excel · Controle Financeiro Pessoal
A2: Lançamentos do mês · tabelas e listas suspensas
A4: Data | B4: Categoria | C4: Descrição | D4: Tipo | E4: Valor
A5: 46205 | B5: Salário | C5: Salário mensal | D5: Entrada | E5: 8500
A6: 46206 | B6: Moradia | C6: Aluguel | D6: Saída | E6: 2200
A7: 46207 | B7: Alimentação | C7: Mercado | D7: Saída | E7: 640.5
A8: 46208 | B8: Assinaturas | C8: Streaming + software | D8: Saída | E8: 189.9
A9: 46209 | B9: Transporte | C9: Combustível | D9: Saída | E9: 320
A10: 46210 | B10: Freelance | C10: Projeto cliente A | D10: Entrada | E10: 1500
A11: 46211 | B11: Lazer | C11: Restaurante | D11: Saída | E11: 210
A12: 46212 | B12: Saúde | C12: Farmácia | D12: Saída | E12: 95.4
A13: 46214 | B13: Alimentação | C13: Delivery | D13: Saída | E13: 78
A14: 46216 | B14: Investimentos | C14: Aporte mensal | D14: Saída | E14: 500
