Workbook

Sheet DASHBOARD
A1: TRUST EXCEL · TRUST CORPORATION
A2: Diagnóstico Financeiro 360
A3: Score · cash bridge · health metrics
B5: RENDA DO MÊS | D5: GASTOS | F5: SALDO (SOBRA) | H5: TAXA DE POUPANÇA | J5: SCORE DE SAÚDE
B6: =Z40 -> 11600 | D6: =Z41 -> 8130 | F6: =Z42 -> 3470 | H6: =Z43 -> 0.29913793 | J6: =Z47 -> 92
B9: =IF(Z47>=80,"🟢 Excelente — patrimônio crescendo. Mantenha os aportes.",IF(Z47>=60,"🟡 Saudável — reduza estilo de vida e aumente aportes.",IF(Z47>=40,"🟠 Atenção — controle gastos e comece a investir.","🔴 Crítico — corte dívidas e despesas não essenciais já."))) -> 🟢 Excelente — patrimônio crescendo. Mantenha os aportes.
B11: CASCATA DO MÊS | R11: Moradia | S11: =SUMIFS(LANCAMENTOS!$E:$E,LANCAMENTOS!$B:$B,R11,LANCAMENTOS!$D:$D,"Saída") -> 2450 | T11: Poupança | U11: =MIN(100,MAX(0,Z43)*400) -> 100
B12: Etapa | C12: Base | D12: Alta | E12: Baixa | F12: Total | G12: Δ | R12: Alimentação | S12: =SUMIFS(LANCAMENTOS!$E:$E,LANCAMENTOS!$B:$B,R12,LANCAMENTOS!$D:$D,"Saída") -> 1180 | T12: Investir | U12: =MIN(100,IFERROR(Z44/Z40,0)*400) -> 51.724138
B13: Renda | C13: 0 | D13: =IF(G13>=0,G13,0) -> 11600 | E13: =IF(G13<0,-G13,0) -> 0 | F13: =G13 -> 11600 | G13: =$Z$40 -> 11600 | R13: Transporte | S13: =SUMIFS(LANCAMENTOS!$E:$E,LANCAMENTOS!$B:$B,R13,LANCAMENTOS!$D:$D,"Saída") -> 560 | T13: Controle | U13: =MAX(0,100-(Z46-0.5)*120) -> 75.896552
B14: Gastos | C14: =IF(G14>=0,F13,F13+G14) -> 3470 | D14: =IF(G14>=0,G14,0) -> 0 | E14: =IF(G14<0,-G14,0) -> 8130 | F14: =F13+G14 -> 3470 | G14: =-$Z$41 -> -8130 | R14: Saúde | S14: =SUMIFS(LANCAMENTOS!$E:$E,LANCAMENTOS!$B:$B,R14,LANCAMENTOS!$D:$D,"Saída") -> 540 | T14: Baixa dívida | U14: =MAX(0,100-IFERROR(Z45/Z40,0)*300) -> 76.724138
B15: Saldo | C15: 0 | D15: =IF(G15>=0,G15,0) -> 3470 | E15: =IF(G15<0,-G15,0) -> 0 | F15: =G15 -> 3470 | G15: =$Z$42 -> 3470 | R15: Educação | S15: =SUMIFS(LANCAMENTOS!$E:$E,LANCAMENTOS!$B:$B,R15,LANCAMENTOS!$D:$D,"Saída") -> 0 | T15: Reserva | U15: =MIN(100,IFERROR(Z42/Z41,0)*100) -> 42.681427
R16: Lazer | S16: =SUMIFS(LANCAMENTOS!$E:$E,LANCAMENTOS!$B:$B,R16,LANCAMENTOS!$D:$D,"Saída") -> 680
R17: Assinaturas | S17: =SUMIFS(LANCAMENTOS!$E:$E,LANCAMENTOS!$B:$B,R17,LANCAMENTOS!$D:$D,"Saída") -> 320
R18: Investimentos | S18: =SUMIFS(LANCAMENTOS!$E:$E,LANCAMENTOS!$B:$B,R18,LANCAMENTOS!$D:$D,"Saída") -> 1500
R19: Dívidas | S19: =SUMIFS(LANCAMENTOS!$E:$E,LANCAMENTOS!$B:$B,R19,LANCAMENTOS!$D:$D,"Saída") -> 900
R20: Salário | S20: =SUMIFS(LANCAMENTOS!$E:$E,LANCAMENTOS!$B:$B,R20,LANCAMENTOS!$D:$D,"Saída") -> 0
R21: Freelance | S21: =SUMIFS(LANCAMENTOS!$E:$E,LANCAMENTOS!$B:$B,R21,LANCAMENTOS!$D:$D,"Saída") -> 0
R22: Outros | S22: =SUMIFS(LANCAMENTOS!$E:$E,LANCAMENTOS!$B:$B,R22,LANCAMENTOS!$D:$D,"Saída") -> 0
B25: SPARKLINES HISTÓRICOS | H25: PROJEÇÃO DE PATRIMÔNIO (12m)
B26: Indicador | C26: Atual | D26: S1 | E26: S2 | F26: S3 | G26: S4 | H26: Ponto | I26: Valor | J26: Spark
B27: Poupança % | C27: =$Z$43*100 -> 29.913793 | D27: 10 | E27: 12 | F27: 15 | G27: 18 | H27: M1 | I27: =PROJECAO!B10 -> 8510 | J27: =IF(OR(I27="",NOT(ISNUMBER(I27))),"",REPT("▬",MAX(1,ROUND((I27-(MIN(I27:I38)))/MAX(0.000000001,(MAX(I27:I38))-(MIN(I27:I38)))*10,0)))) -> ▬
B28: Score | C28: =$Z$47 -> 92 | D28: 55 | E28: 62 | F28: 68 | G28: 74 | H28: M2 | I28: =PROJECAO!B11 -> 12048.08 | J28: =IF(OR(I28="",NOT(ISNUMBER(I28))),"",REPT("▬",MAX(1,ROUND((I28-(MIN(I27:I38)))/MAX(0.000000001,(MAX(I27:I38))-(MIN(I27:I38)))*10,0)))) -> ▬
B29: Investimentos | C29: =$Z$44 -> 1500 | D29: 400 | E29: 600 | F29: 800 | G29: 1000 | H29: M3 | I29: =PROJECAO!B12 -> 15614.465 | J29: =IF(OR(I29="",NOT(ISNUMBER(I29))),"",REPT("▬",MAX(1,ROUND((I29-(MIN(I27:I38)))/MAX(0.000000001,(MAX(I27:I38))-(MIN(I27:I38)))*10,0)))) -> ▬▬
B30: Dívidas | C30: =$Z$45 -> 900 | D30: 1400 | E30: 1200 | F30: 1100 | G30: 1000 | H30: M4 | I30: =PROJECAO!B13 -> 19209.38 | J30: =IF(OR(I30="",NOT(ISNUMBER(I30))),"",REPT("▬",MAX(1,ROUND((I30-(MIN(I27:I38)))/MAX(0.000000001,(MAX(I27:I38))-(MIN(I27:I38)))*10,0)))) -> ▬▬▬
H31: M5 | I31: =PROJECAO!B14 -> 22833.055 | J31: =IF(OR(I31="",NOT(ISNUMBER(I31))),"",REPT("▬",MAX(1,ROUND((I31-(MIN(I27:I38)))/MAX(0.000000001,(MAX(I27:I38))-(MIN(I27:I38)))*10,0)))) -> ▬▬▬▬
H32: M6 | I32: =PROJECAO!B15 -> 26485.72 | J32: =IF(OR(I32="",NOT(ISNUMBER(I32))),"",REPT("▬",MAX(1,ROUND((I32-(MIN(I27:I38)))/MAX(0.000000001,(MAX(I27:I38))-(MIN(I27:I38)))*10,0)))) -> ▬▬▬▬
H33: M7 | I33: =PROJECAO!B16 -> 30167.606 | J33: =IF(OR(I33="",NOT(ISNUMBER(I33))),"",REPT("▬",MAX(1,ROUND((I33-(MIN(I27:I38)))/MAX(0.000000001,(MAX(I27:I38))-(MIN(I27:I38)))*10,0)))) -> ▬▬▬▬▬
H34: M8 | I34: =PROJECAO!B17 -> 33878.946 | J34: =IF(OR(I34="",NOT(ISNUMBER(I34))),"",REPT("▬",MAX(1,ROUND((I34-(MIN(I27:I38)))/MAX(0.000000001,(MAX(I27:I38))-(MIN(I27:I38)))*10,0)))) -> ▬▬▬▬▬▬
H35: M9 | I35: =PROJECAO!B18 -> 37619.978 | J35: =IF(OR(I35="",NOT(ISNUMBER(I35))),"",REPT("▬",MAX(1,ROUND((I35-(MIN(I27:I38)))/MAX(0.000000001,(MAX(I27:I38))-(MIN(I27:I38)))*10,0)))) -> ▬▬▬▬▬▬▬
H36: M10 | I36: =PROJECAO!B19 -> 41390.938 | J36: =IF(OR(I36="",NOT(ISNUMBER(I36))),"",REPT("▬",MAX(1,ROUND((I36-(MIN(I27:I38)))/MAX(0.000000001,(MAX(I27:I38))-(MIN(I27:I38)))*10,0)))) -> ▬▬▬▬▬▬▬▬
H37: M11 | I37: =PROJECAO!B20 -> 45192.065 | J37: =IF(OR(I37="",NOT(ISNUMBER(I37))),"",REPT("▬",MAX(1,ROUND((I37-(MIN(I27:I38)))/MAX(0.000000001,(MAX(I27:I38))-(MIN(I27:I38)))*10,0)))) -> ▬▬▬▬▬▬▬▬▬
H38: M12 | I38: =PROJECAO!B21 -> 49023.602 | J38: =IF(OR(I38="",NOT(ISNUMBER(I38))),"",REPT("▬",MAX(1,ROUND((I38-(MIN(I27:I38)))/MAX(0.000000001,(MAX(I27:I38))-(MIN(I27:I38)))*10,0)))) -> ▬▬▬▬▬▬▬▬▬▬
Z40: =SUMIF(LANCAMENTOS!D:D,"Entrada",LANCAMENTOS!E:E) -> 11600
Z41: =SUMIF(LANCAMENTOS!D:D,"Saída",LANCAMENTOS!E:E) -> 8130
Z42: =Z40-Z41 -> 3470
Z43: =IFERROR(Z42/Z40,0) -> 0.29913793
Z44: =SUMIF(LANCAMENTOS!B:B,"Investimentos",LANCAMENTOS!E:E) -> 1500
Z45: =SUMIF(LANCAMENTOS!B:B,"Dívidas",LANCAMENTOS!E:E) -> 900
Z46: =IFERROR(Z41/Z40,1) -> 0.70086207
Z47: =ROUND(MAX(0,MIN(100,MIN(40,MAX(0,Z43)*160)+MIN(25,IFERROR(Z44/Z40,0)*250)+MAX(0,20-IFERROR(Z45/Z40,0)*100)+MAX(0,15-(Z46-0.7)*50))),0) -> 92

Sheet CONFIG
A1: CATEGORIAS & PESOS DO DIAGNÓSTICO
A3: Categoria | B3: Teto ideal % | C3: Tipo | D3: Tipos de lançamento
A4: Moradia | B4: 0.3 | C4: Essencial | D4: Entrada
A5: Alimentação | B5: 0.15 | C5: Essencial | D5: Saída
A6: Transporte | B6: 0.1 | C6: Essencial
A7: Saúde | B7: 0.08 | C7: Essencial
A8: Educação | B8: 0.08 | C8: Investimento
A9: Lazer | B9: 0.08 | C9: Estilo de vida
A10: Assinaturas | B10: 0.05 | C10: Estilo de vida
A11: Investimentos | B11: 0.15 | C11: Futuro
A12: Dívidas | B12: 0.1 | C12: Risco
A13: Salário | B13: 0 | C13: Entrada
A14: Freelance | B14: 0 | C14: Entrada
A15: Outros | B15: 0.05 | C15: Estilo de vida

Sheet LANCAMENTOS
A1: TRUST EXCEL · TRUST CORPORATION
A2: Lançamentos
A3: Preencha aqui — o diagnóstico calcula sozinho
A5: Data | B5: Categoria | C5: Descrição | D5: Tipo | E5: Valor | F5: Alerta teto
A6: 46205 | B6: Salário | C6: Salário mensal | D6: Entrada | E6: 9200 | F6: =IF(D6<>"Saída","",IF(E6>SUMIF($D$6:$D$205,"Entrada",$E$6:$E$205)*IFERROR(VLOOKUP(B6,CONFIG!$A$4:$B$15,2,0),1),"⚠ teto","ok"))
A7: 46206 | B7: Moradia | C7: Aluguel + condomínio | D7: Saída | E7: 2450 | F7: =IF(D7<>"Saída","",IF(E7>SUMIF($D$6:$D$205,"Entrada",$E$6:$E$205)*IFERROR(VLOOKUP(B7,CONFIG!$A$4:$B$15,2,0),1),"⚠ teto","ok")) -> ok
A8: 46207 | B8: Alimentação | C8: Mercado do mês | D8: Saída | E8: 1180 | F8: =IF(D8<>"Saída","",IF(E8>SUMIF($D$6:$D$205,"Entrada",$E$6:$E$205)*IFERROR(VLOOKUP(B8,CONFIG!$A$4:$B$15,2,0),1),"⚠ teto","ok")) -> ok
A9: 46208 | B9: Assinaturas | C9: Softwares e streaming | D9: Saída | E9: 320 | F9: =IF(D9<>"Saída","",IF(E9>SUMIF($D$6:$D$205,"Entrada",$E$6:$E$205)*IFERROR(VLOOKUP(B9,CONFIG!$A$4:$B$15,2,0),1),"⚠ teto","ok")) -> ok
A10: 46209 | B10: Transporte | C10: Combustível + app | D10: Saída | E10: 560 | F10: =IF(D10<>"Saída","",IF(E10>SUMIF($D$6:$D$205,"Entrada",$E$6:$E$205)*IFERROR(VLOOKUP(B10,CONFIG!$A$4:$B$15,2,0),1),"⚠ teto","ok")) -> ok
A11: 46210 | B11: Freelance | C11: Projeto avulso | D11: Entrada | E11: 2400 | F11: =IF(D11<>"Saída","",IF(E11>SUMIF($D$6:$D$205,"Entrada",$E$6:$E$205)*IFERROR(VLOOKUP(B11,CONFIG!$A$4:$B$15,2,0),1),"⚠ teto","ok"))
A12: 46211 | B12: Lazer | C12: Restaurantes | D12: Saída | E12: 680 | F12: =IF(D12<>"Saída","",IF(E12>SUMIF($D$6:$D$205,"Entrada",$E$6:$E$205)*IFERROR(VLOOKUP(B12,CONFIG!$A$4:$B$15,2,0),1),"⚠ teto","ok")) -> ok
A13: 46212 | B13: Saúde | C13: Plano + farmácia | D13: Saída | E13: 540 | F13: =IF(D13<>"Saída","",IF(E13>SUMIF($D$6:$D$205,"Entrada",$E$6:$E$205)*IFERROR(VLOOKUP(B13,CONFIG!$A$4:$B$15,2,0),1),"⚠ teto","ok")) -> ok
A14: 46214 | B14: Investimentos | C14: Aporte carteira | D14: Saída | E14: 1500 | F14: =IF(D14<>"Saída","",IF(E14>SUMIF($D$6:$D$205,"Entrada",$E$6:$E$205)*IFERROR(VLOOKUP(B14,CONFIG!$A$4:$B$15,2,0),1),"⚠ teto","ok")) -> ok
A15: 46216 | B15: Dívidas | C15: Cartão parcelado | D15: Saída | E15: 900 | F15: =IF(D15<>"Saída","",IF(E15>SUMIF($D$6:$D$205,"Entrada",$E$6:$E$205)*IFERROR(VLOOKUP(B15,CONFIG!$A$4:$B$15,2,0),1),"⚠ teto","ok")) -> ok
F16: =IF(D16<>"Saída","",IF(E16>SUMIF($D$6:$D$205,"Entrada",$E$6:$E$205)*IFERROR(VLOOKUP(B16,CONFIG!$A$4:$B$15,2,0),1),"⚠ teto","ok"))
F17: =IF(D17<>"Saída","",IF(E17>SUMIF($D$6:$D$205,"Entrada",$E$6:$E$205)*IFERROR(VLOOKUP(B17,CONFIG!$A$4:$B$15,2,0),1),"⚠ teto","ok"))
F18: =IF(D18<>"Saída","",IF(E18>SUMIF($D$6:$D$205,"Entrada",$E$6:$E$205)*IFERROR(VLOOKUP(B18,CONFIG!$A$4:$B$15,2,0),1),"⚠ teto","ok"))
F19: =IF(D19<>"Saída","",IF(E19>SUMIF($D$6:$D$205,"Entrada",$E$6:$E$205)*IFERROR(VLOOKUP(B19,CONFIG!$A$4:$B$15,2,0),1),"⚠ teto","ok"))
F20: =IF(D20<>"Saída","",IF(E20>SUMIF($D$6:$D$205,"Entrada",$E$6:$E$205)*IFERROR(VLOOKUP(B20,CONFIG!$A$4:$B$15,2,0),1),"⚠ teto","ok"))
F21: =IF(D21<>"Saída","",IF(E21>SUMIF($D$6:$D$205,"Entrada",$E$6:$E$205)*IFERROR(VLOOKUP(B21,CONFIG!$A$4:$B$15,2,0),1),"⚠ teto","ok"))
F22: =IF(D22<>"Saída","",IF(E22>SUMIF($D$6:$D$205,"Entrada",$E$6:$E$205)*IFERROR(VLOOKUP(B22,CONFIG!$A$4:$B$15,2,0),1),"⚠ teto","ok"))
F23: =IF(D23<>"Saída","",IF(E23>SUMIF($D$6:$D$205,"Entrada",$E$6:$E$205)*IFERROR(VLOOKUP(B23,CONFIG!$A$4:$B$15,2,0),1),"⚠ teto","ok"))
F24: =IF(D24<>"Saída","",IF(E24>SUMIF($D$6:$D$205,"Entrada",$E$6:$E$205)*IFERROR(VLOOKUP(B24,CONFIG!$A$4:$B$15,2,0),1),"⚠ teto","ok"))
F25: =IF(D25<>"Saída","",IF(E25>SUMIF($D$6:$D$205,"Entrada",$E$6:$E$205)*IFERROR(VLOOKUP(B25,CONFIG!$A$4:$B$15,2,0),1),"⚠ teto","ok"))
F26: =IF(D26<>"Saída","",IF(E26>SUMIF($D$6:$D$205,"Entrada",$E$6:$E$205)*IFERROR(VLOOKUP(B26,CONFIG!$A$4:$B$15,2,0),1),"⚠ teto","ok"))
F27: =IF(D27<>"Saída","",IF(E27>SUMIF($D$6:$D$205,"Entrada",$E$6:$E$205)*IFERROR(VLOOKUP(B27,CONFIG!$A$4:$B$15,2,0),1),"⚠ teto","ok"))
... F126: =IF(D126<>"Saída","",IF(E126>SUMIF($D$6:$D$205,"Entrada",$E$6:$E$205)*IFERROR(VLOOKUP(B126,CONFIG!$A$4:$B$15,2,0),1),"⚠ teto","ok"))

Sheet PROJECAO
A1: TRUST EXCEL · TRUST CORPORATION
A2: Projeção de Patrimônio
A3: Sobra mensal reinvestida
A5: Aporte mensal | B5: =DASHBOARD!Z42 -> 3470
A6: Rend. a.m. | B6: 0.008
A7: Inicial | B7: 5000
A9: Mês | B9: Patrimônio
A10: 1 | B10: =$B$7*(1+$B$6)+MAX(0,$B$5) -> 8510
A11: 2 | B11: =B10*(1+$B$6)+MAX(0,$B$5) -> 12048.08
A12: 3 | B12: =B11*(1+$B$6)+MAX(0,$B$5) -> 15614.465
A13: 4 | B13: =B12*(1+$B$6)+MAX(0,$B$5) -> 19209.38
A14: 5 | B14: =B13*(1+$B$6)+MAX(0,$B$5) -> 22833.055
A15: 6 | B15: =B14*(1+$B$6)+MAX(0,$B$5) -> 26485.72
A16: 7 | B16: =B15*(1+$B$6)+MAX(0,$B$5) -> 30167.606
A17: 8 | B17: =B16*(1+$B$6)+MAX(0,$B$5) -> 33878.946
A18: 9 | B18: =B17*(1+$B$6)+MAX(0,$B$5) -> 37619.978
A19: 10 | B19: =B18*(1+$B$6)+MAX(0,$B$5) -> 41390.938
A20: 11 | B20: =B19*(1+$B$6)+MAX(0,$B$5) -> 45192.065
A21: 12 | B21: =B20*(1+$B$6)+MAX(0,$B$5) -> 49023.602
