Workbook

Sheet DASHBOARD
A1: TRUST EXCEL · TRUST CORPORATION
A2: Simulador de Fluxo de Caixa
A3: Cenários dinâmicos · runway · ruptura
B5: CENÁRIO: | D5: SALDO HOJE | F5: MENOR SALDO | H5: ENTRADAS PREV. | J5: SAÍDAS PREV. | L5: RUNWAY
B6: Realista | D6: =Z40 -> 16950 | F6: =Z41 -> #VALUE! | H6: =Z43 -> #VALUE! | J6: =Z44 -> 5450 | L6: =Z45 -> 279.90826
B7: aplicado às entradas | F7: vale do caixa
B9: =IF(Z41<0,CONCATENATE("🔴 RUPTURA prevista em ",TEXT(Z42,"dd/mm")," — corte saídas."),IF(Z41<5000,"🟠 Caixa aperta no período. Monitore de perto.","🟢 Projeção saudável no cenário selecionado.")) -> #VALUE!
B11: CASCATA DE CAIXA | F11: CURVA DE SALDO ACUMULADO
B12: Etapa | C12: Base | D12: Alta | E12: Baixa | F12: Total | G12: Δ
B13: Saldo hoje | C13: 0 | D13: =IF(G13>=0,G13,0) -> 16950 | E13: =IF(G13<0,-G13,0) -> 0 | F13: =G13 -> 16950 | G13: =$Z$40 -> 16950
B14: + Entradas | C14: =IF(G14>=0,F13,F13+G14) -> #VALUE! | D14: =IF(G14>=0,G14,0) -> #VALUE! | E14: =IF(G14<0,-G14,0) -> #VALUE! | F14: =F13+G14 -> #VALUE! | G14: =$Z$43 -> #VALUE!
B15: − Saídas | C15: =IF(G15>=0,F14,F14+G15) -> #VALUE! | D15: =IF(G15>=0,G15,0) -> 0 | E15: =IF(G15<0,-G15,0) -> 5450 | F15: =F14+G15 -> #VALUE! | G15: =-$Z$44 -> -5450
B16: Saldo 90d | C16: 0 | D16: =IF(G16>=0,G16,0) -> #VALUE! | E16: =IF(G16<0,-G16,0) -> #VALUE! | F16: =G16 -> #VALUE! | G16: =$Z$40+$Z$43-$Z$44 -> #VALUE!
B25: MINI-SPARKLINES | H25: SPARK DA CURVA
B26: Indicador | C26: Atual | D26: S1 | E26: S2 | F26: S3 | G26: S4 | H26: Ponto | I26: Valor | J26: Spark
B27: Runway d | C27: =$Z$45 -> 279.90826 | D27: 60 | E27: 70 | F27: 80 | G27: 90 | H27: S1 | I27: =IF(MOVIMENTOS!G6="","",MOVIMENTOS!G6) -> 19200 | J27: =IF(OR(I27="",NOT(ISNUMBER(I27))),"",REPT("▬",MAX(1,ROUND((I27-(MIN(I27:I32)))/MAX(0.000000001,(MAX(I27:I32))-(MIN(I27:I32)))*10,0)))) -> #VALUE!
B28: Menor saldo | C28: =$Z$41 -> #VALUE! | D28: 18000 | E28: 17000 | F28: 16000 | G28: 15500 | H28: S2 | I28: =IF(MOVIMENTOS!G8="","",MOVIMENTOS!G8) -> 18400 | J28: =IF(OR(I28="",NOT(ISNUMBER(I28))),"",REPT("▬",MAX(1,ROUND((I28-(MIN(I27:I32)))/MAX(0.000000001,(MAX(I27:I32))-(MIN(I27:I32)))*10,0)))) -> #VALUE!
B29: Entradas | C29: =$Z$43 -> #VALUE! | D29: 15000 | E29: 17000 | F29: 19000 | G29: 20000 | H29: S3 | I29: =IF(MOVIMENTOS!G10="","",MOVIMENTOS!G10) -> #VALUE! | J29: =IF(OR(I29="",NOT(ISNUMBER(I29))),"",REPT("▬",MAX(1,ROUND((I29-(MIN(I27:I32)))/MAX(0.000000001,(MAX(I27:I32))-(MIN(I27:I32)))*10,0)))) -> #VALUE!
H30: S4 | I30: =IF(MOVIMENTOS!G12="","",MOVIMENTOS!G12) -> #VALUE! | J30: =IF(OR(I30="",NOT(ISNUMBER(I30))),"",REPT("▬",MAX(1,ROUND((I30-(MIN(I27:I32)))/MAX(0.000000001,(MAX(I27:I32))-(MIN(I27:I32)))*10,0)))) -> #VALUE!
H31: S5 | I31: =IF(MOVIMENTOS!G14="","",MOVIMENTOS!G14) -> #VALUE! | J31: =IF(OR(I31="",NOT(ISNUMBER(I31))),"",REPT("▬",MAX(1,ROUND((I31-(MIN(I27:I32)))/MAX(0.000000001,(MAX(I27:I32))-(MIN(I27:I32)))*10,0)))) -> #VALUE!
H32: S6 | I32: =IF(MOVIMENTOS!G16="","",MOVIMENTOS!G16) | J32: =IF(OR(I32="",NOT(ISNUMBER(I32))),"",REPT("▬",MAX(1,ROUND((I32-(MIN(I27:I32)))/MAX(0.000000001,(MAX(I27:I32))-(MIN(I27:I32)))*10,0))))
Z40: =LOOKUP(2,1/(MOVIMENTOS!E6:E156="Realizado"),MOVIMENTOS!G6:G156) -> 16950
Z41: =MIN(MOVIMENTOS!G6:G156) -> #VALUE!
Z42: =INDEX(MOVIMENTOS!A6:A156,MATCH(MIN(MOVIMENTOS!G6:G156),MOVIMENTOS!G6:G156,0)) -> #VALUE!
Z43: =SUMIFS(MOVIMENTOS!C:C,MOVIMENTOS!E:E,"Previsto")*D5 -> #VALUE!
Z44: =SUMIFS(MOVIMENTOS!D:D,MOVIMENTOS!E:E,"Previsto") -> 5450
Z45: =IFERROR(Z40/(Z44/90),999) -> 279.90826

Sheet MOVIMENTOS
A1: TRUST EXCEL · TRUST CORPORATION
A2: Movimentos
A3: Realizados e previstos — base do simulador
A5: Data | B5: Descrição | C5: Entrada | D5: Saída | E5: Status | F5: Categoria | G5: Saldo acumulado
A6: 46211 | B6: Recebimento A | C6: 4200 | E6: Realizado | F6: Vendas | G6: =IF(B6="","",15000+IF(E6="Previsto",IF(C6="",0,C6)*DASHBOARD!$D$5,IF(C6="",0,C6))-IF(D6="",0,D6)) -> 19200
A7: 46215 | B7: Folha/Impostos | D7: 3900 | E7: Realizado | F7: Pessoal | G7: =IF(B7="","",G6+IF(E7="Previsto",IF(C7="",0,C7)*DASHBOARD!$D$5,IF(C7="",0,C7))-IF(D7="",0,D7)) -> 15300
A8: 46219 | B8: Recebimento B | C8: 3100 | E8: Realizado | F8: Vendas | G8: =IF(B8="","",G7+IF(E8="Previsto",IF(C8="",0,C8)*DASHBOARD!$D$5,IF(C8="",0,C8))-IF(D8="",0,D8)) -> 18400
A9: 46223 | B9: Fornecedores | D9: 1450 | E9: Realizado | F9: Custo | G9: =IF(B9="","",G8+IF(E9="Previsto",IF(C9="",0,C9)*DASHBOARD!$D$5,IF(C9="",0,C9))-IF(D9="",0,D9)) -> 16950
A10: 46228 | B10: Recebimento prev. | C10: 4800 | E10: Previsto | F10: Vendas | G10: =IF(B10="","",G9+IF(E10="Previsto",IF(C10="",0,C10)*DASHBOARD!$D$5,IF(C10="",0,C10))-IF(D10="",0,D10)) -> #VALUE!
A11: 46231 | B11: Aluguel | D11: 2400 | E11: Previsto | F11: Fixo | G11: =IF(B11="","",G10+IF(E11="Previsto",IF(C11="",0,C11)*DASHBOARD!$D$5,IF(C11="",0,C11))-IF(D11="",0,D11)) -> #VALUE!
A12: 46234 | B12: Impostos | D12: 1250 | E12: Previsto | F12: Imposto | G12: =IF(B12="","",G11+IF(E12="Previsto",IF(C12="",0,C12)*DASHBOARD!$D$5,IF(C12="",0,C12))-IF(D12="",0,D12)) -> #VALUE!
A13: 46239 | B13: Contrato novo | C13: 5200 | E13: Previsto | F13: Vendas | G13: =IF(B13="","",G12+IF(E13="Previsto",IF(C13="",0,C13)*DASHBOARD!$D$5,IF(C13="",0,C13))-IF(D13="",0,D13)) -> #VALUE!
A14: 46245 | B14: Marketing | D14: 1800 | E14: Previsto | F14: Growth | G14: =IF(B14="","",G13+IF(E14="Previsto",IF(C14="",0,C14)*DASHBOARD!$D$5,IF(C14="",0,C14))-IF(D14="",0,D14)) -> #VALUE!
A15: 46252 | B15: Assinatura | C15: 2200 | E15: Previsto | F15: Recorrente | G15: =IF(B15="","",G14+IF(E15="Previsto",IF(C15="",0,C15)*DASHBOARD!$D$5,IF(C15="",0,C15))-IF(D15="",0,D15)) -> #VALUE!
G16: =IF(B16="","",G15+IF(E16="Previsto",IF(C16="",0,C16)*DASHBOARD!$D$5,IF(C16="",0,C16))-IF(D16="",0,D16))
G17: =IF(B17="","",G16+IF(E17="Previsto",IF(C17="",0,C17)*DASHBOARD!$D$5,IF(C17="",0,C17))-IF(D17="",0,D17))
G18: =IF(B18="","",G17+IF(E18="Previsto",IF(C18="",0,C18)*DASHBOARD!$D$5,IF(C18="",0,C18))-IF(D18="",0,D18))
G19: =IF(B19="","",G18+IF(E19="Previsto",IF(C19="",0,C19)*DASHBOARD!$D$5,IF(C19="",0,C19))-IF(D19="",0,D19))
G20: =IF(B20="","",G19+IF(E20="Previsto",IF(C20="",0,C20)*DASHBOARD!$D$5,IF(C20="",0,C20))-IF(D20="",0,D20))
G21: =IF(B21="","",G20+IF(E21="Previsto",IF(C21="",0,C21)*DASHBOARD!$D$5,IF(C21="",0,C21))-IF(D21="",0,D21))
G22: =IF(B22="","",G21+IF(E22="Previsto",IF(C22="",0,C22)*DASHBOARD!$D$5,IF(C22="",0,C22))-IF(D22="",0,D22))
G23: =IF(B23="","",G22+IF(E23="Previsto",IF(C23="",0,C23)*DASHBOARD!$D$5,IF(C23="",0,C23))-IF(D23="",0,D23))
G24: =IF(B24="","",G23+IF(E24="Previsto",IF(C24="",0,C24)*DASHBOARD!$D$5,IF(C24="",0,C24))-IF(D24="",0,D24))
G25: =IF(B25="","",G24+IF(E25="Previsto",IF(C25="",0,C25)*DASHBOARD!$D$5,IF(C25="",0,C25))-IF(D25="",0,D25))
G26: =IF(B26="","",G25+IF(E26="Previsto",IF(C26="",0,C26)*DASHBOARD!$D$5,IF(C26="",0,C26))-IF(D26="",0,D26))
G27: =IF(B27="","",G26+IF(E27="Previsto",IF(C27="",0,C27)*DASHBOARD!$D$5,IF(C27="",0,C27))-IF(D27="",0,D27))
... G156: =IF(B156="","",G155+IF(E156="Previsto",IF(C156="",0,C156)*DASHBOARD!$D$5,IF(C156="",0,C156))-IF(D156="",0,D156))
