Workbook

Sheet DASHBOARD
A1: TRUST EXCEL · TRUST CORPORATION
A2: Motor de Precificação
A3: Valor/hora · break-even · cenários de proposta
B5: VALOR DA HORA | D5: BREAK-EVEN (un.) | F5: FATURAM. MÍNIMO | H5: MARGEM CONTRIB. | J5: PREÇO-ALVO
B6: =Z40 -> 225 | D6: =Z41 -> 61.403509 | F6: =Z42 -> 9149.1228 | H6: =Z43 -> 0.76510067 | J6: =ENTRADAS!E8 -> 1200
B9: =CONCATENATE("Para bater o preço-alvo com 30% de margem, gaste no máx. ",TEXT(MAX(0,((ENTRADAS!E8*0.7)-ENTRADAS!E7)/ENTRADAS!B11),"0.0")," horas.") -> Para bater o preço-alvo com 30% de margem, gaste no máx. 03 horas.
B11: CASCATA PREÇO IDEAL | F11: 3 CENÁRIOS DE PROPOSTA
B12: Etapa | C12: Base | D12: Alta | E12: Baixa | F12: Cenário | G12: Margem | H12: Preço sugerido | I12: Uso
B13: Custo entrega | C13: 0 | D13: =IF(G13>=0,G13,0) -> 0.15 | E13: =IF(G13<0,-G13,0) -> 0 | F13: Mínimo | G13: 0.15 | H13: =$Z$44/(1-G13) -> 31905.882 | I13: Entrar
B14: + Margem 30% | C14: =IF(G14>=0,F13,F13+G14) -> Mínimo | D14: =IF(G14>=0,G14,0) -> 0.3 | E14: =IF(G14<0,-G14,0) -> 0 | F14: Ideal | G14: 0.3 | H14: =$Z$44/(1-G14) -> 38742.857 | I14: Saudável
B15: Preço ideal | C15: 0 | D15: =IF(G15>=0,G15,0) -> 0.5 | E15: =IF(G15<0,-G15,0) -> 0 | F15: Premium | G15: 0.5 | H15: =$Z$44/(1-G15) -> 54240 | I15: Urgência
B25: MINI-SPARKLINES | H25: SPARK SENSIBILIDADE
B26: Indicador | C26: Atual | D26: S1 | E26: S2 | F26: S3 | G26: S4 | H26: Ponto | I26: Valor | J26: Spark
B27: Valor/hora | C27: =$Z$40 -> 225 | D27: 180 | E27: 190 | F27: 200 | G27: 210 | H27: 10% | I27: =$Z$44/(1-0.1) -> 30133.333 | J27: =IF(OR(I27="",NOT(ISNUMBER(I27))),"",REPT("▬",MAX(1,ROUND((I27-(MIN(I27:I31)))/MAX(0.000000001,(MAX(I27:I31))-(MIN(I27:I31)))*10,0)))) -> ▬
B28: Break-even | C28: =$Z$41 -> 61.403509 | D28: 80 | E28: 75 | F28: 70 | G28: 65 | H28: 20% | I28: =$Z$44/(1-0.2) -> 33900 | J28: =IF(OR(I28="",NOT(ISNUMBER(I28))),"",REPT("▬",MAX(1,ROUND((I28-(MIN(I27:I31)))/MAX(0.000000001,(MAX(I27:I31))-(MIN(I27:I31)))*10,0)))) -> ▬▬
B29: Margem % | C29: =$Z$43*100 -> 76.510067 | D29: 60 | E29: 65 | F29: 70 | G29: 72 | H29: 30% | I29: =$Z$44/(1-0.3) -> 38742.857 | J29: =IF(OR(I29="",NOT(ISNUMBER(I29))),"",REPT("▬",MAX(1,ROUND((I29-(MIN(I27:I31)))/MAX(0.000000001,(MAX(I27:I31))-(MIN(I27:I31)))*10,0)))) -> ▬▬▬▬
H30: 40% | I30: =$Z$44/(1-0.4) -> 45200 | J30: =IF(OR(I30="",NOT(ISNUMBER(I30))),"",REPT("▬",MAX(1,ROUND((I30-(MIN(I27:I31)))/MAX(0.000000001,(MAX(I27:I31))-(MIN(I27:I31)))*10,0)))) -> ▬▬▬▬▬▬
H31: 50% | I31: =$Z$44/(1-0.5) -> 54240 | J31: =IF(OR(I31="",NOT(ISNUMBER(I31))),"",REPT("▬",MAX(1,ROUND((I31-(MIN(I27:I31)))/MAX(0.000000001,(MAX(I27:I31))-(MIN(I27:I31)))*10,0)))) -> ▬▬▬▬▬▬▬▬▬▬
Z40: =ENTRADAS!B11 -> 225
Z41: =IFERROR(ENTRADAS!B6/ENTRADAS!B12,0) -> 61.403509
Z42: =Z41*ENTRADAS!B9 -> 9149.1228
Z43: =ENTRADAS!B13 -> 0.76510067
Z44: =(ENTRADAS!B7*ENTRADAS!B11)+ENTRADAS!E7 -> 27120

Sheet ENTRADAS
A1: TRUST EXCEL · TRUST CORPORATION
A2: Parâmetros de Precificação
A3: Ajuste as entradas para recalcular margens
A5: Renda desejada / mês | B5: 20000 | D5: Nome do serviço (avulso) | E5: Plano Pro
A6: Custos fixos / mês | B6: 7000 | D6: Horas por entrega | E6: 6
A7: Horas produtivas / mês | B7: 120 | D7: Custos extras / entrega | E7: 120
A8: Custo variável / unidade | B8: 35 | D8: Preço-alvo do cliente | E8: 1200
A9: Preço de venda padrão | B9: 149
B11: =(B5+B6)/B7 -> 225
B12: =B9-B8 -> 114
B13: =IFERROR(B12/B9,0) -> 0.76510067
